Metadata-Version: 2.1
Name: cvrf2csaf
Version: 1.0.0
Summary: Converts CVRF XML documents to CSAF JSON documents
Home-page: https://github.com/csaf-tools/CVRF-CSAF-Converter/
Author: Deutsche Telekom Security GmbH
Author-email: cti@t-mobile.cz
License: UNKNOWN
Project-URL: Bug Tracker, https://github.com/csaf-tools/CVRF-CSAF-Converter/issues
Platform: UNKNOWN
Classifier: Programming Language :: Python :: 3
Classifier: License :: OSI Approved :: MIT License
Classifier: Operating System :: OS Independent
Requires-Python: >=3.6
